tree.py
treezor-0.1.1.dist-info/METADATA
treezor-0.1.1.dist-info/WHEEL
treezor-0.1.1.dist-info/entry_points.txt
treezor-0.1.1.dist-info/top_level.txt
treezor-0.1.1.dist-info/RECORD
